LICENSE
MANIFEST.in
README.md
install_script.py
setup.py
kdPythonInstaller/__init__.py
kdPythonInstaller/get-pip.py
kdPythonInstaller/kdPythonInstaller.py
kdPythonInstaller.egg-info/PKG-INFO
kdPythonInstaller.egg-info/SOURCES.txt
kdPythonInstaller.egg-info/dependency_links.txt
kdPythonInstaller.egg-info/entry_points.txt
kdPythonInstaller.egg-info/not-zip-safe
kdPythonInstaller.egg-info/top_level.txt